eoxelements/__init__.py
eoxelements/_version.py
eoxelements/chart.py
eoxelements/layercontrol.py
eoxelements/layouts.py
eoxelements/map.py
eoxelements-0.2.15.dist-info/licenses/LICENSE
eoxelements-0.2.15.dist-info/METADATA
eoxelements-0.2.15.dist-info/WHEEL
eoxelements-0.2.15.dist-info/top_level.txt
eoxelements-0.2.15.dist-info/RECORD
