Metadata-Version: 2.4
Name: eoxelements
Version: 0.2.15
Summary: Jupyter notebook wrapper for EOxElements web components
Author-email: EOX <silvester.pari@eox.at>
License-Expression: MIT
Project-URL: Homepage, https://github.com/EOX-A/EOxElements-Jupyter
Project-URL: Issues, https://github.com/EOX-A/EOxElements-Jupyter/issues
Requires-Python: >=3.8
License-File: LICENSE
Requires-Dist: anywidget>=0.9.0
Requires-Dist: ipywidgets>=8.0.0
Requires-Dist: traitlets
Dynamic: license-file
